setup.cfg
setup.py
dnaseq_validation/__init__.py
dnaseq_validation/__main__.py
dnaseq_validation/main.py
dnaseq_validation.egg-info/PKG-INFO
dnaseq_validation.egg-info/SOURCES.txt
dnaseq_validation.egg-info/dependency_links.txt
dnaseq_validation.egg-info/entry_points.txt
dnaseq_validation.egg-info/top_level.txt