Metadata-Version: 1.1
Name: dnaseq-validation
Version: 0.2
Summary: validate dnaseq workflow based on fastqc, picard and samtools metrics
Home-page: https://github.com/NCI-GDC/dnaseq_validation
Author: Jeremiah H. Savage
Author-email: jeremiahsavage@gmail.com
License: Apache 2.0
Platform: UNKNOWN
Classifier: Development Status :: 3 - Alpha
Classifier: Intended Audience :: Developers
Classifier: License :: OSI Approved :: Apache Software License
Classifier: Programming Language :: Python
Classifier: Programming Language :: Python :: 3
